specstream/__init__.py
specstream/deployment.py
specstream/inference_engine.py
specstream/lora_integration.py
specstream/multi_stream_attention.py
specstream/py.typed
specstream/speculative_streaming.py
specstream/training.py
specstream/tree_pruning.py
specstream-1.0.0.dist-info/licenses/LICENSE
specstream-1.0.0.dist-info/METADATA
specstream-1.0.0.dist-info/WHEEL
specstream-1.0.0.dist-info/top_level.txt
specstream-1.0.0.dist-info/RECORD
