Metadata-Version: 2.4
Name: specstream
Version: 1.0.0
Summary: Fast LLM inference with 2.8x speedup using speculative decoding
Author-email: SpecStream Team <research@specstream.ai>
Maintainer-email: SpecStream Team <research@specstream.ai>
License-Expression: MIT
Project-URL: Homepage, https://github.com/llmsresearch/specstream
Project-URL: Documentation, https://github.com/llmsresearch/specstream/blob/main/README.md
Project-URL: Repository, https://github.com/llmsresearch/specstream
Project-URL: Bug Tracker, https://github.com/llmsresearch/specstream/issues
Project-URL: Changelog, https://github.com/llmsresearch/specstream/blob/main/CHANGELOG.md
Keywords: llm,inference,speculative-decoding,transformer,deep-learning,pytorch,nlp,ai
Classifier: Development Status :: 4 - Beta
Classifier: Intended Audience :: Developers
Classifier: Intended Audience :: Science/Research
Classifier: Operating System :: OS Independent
Classifier: Programming Language :: Python :: 3
Classifier: Programming Language :: Python :: 3.9
Classifier: Programming Language :: Python :: 3.10
Classifier: Programming Language :: Python :: 3.11
Classifier: Programming Language :: Python :: 3.12
Classifier: Topic :: Scientific/Engineering :: Artificial Intelligence
Classifier: Topic :: Software Development :: Libraries :: Python Modules
Requires-Python: >=3.9
License-File: LICENSE
Requires-Dist: torch>=2.0.0
Requires-Dist: transformers>=4.25.0
Requires-Dist: tokenizers>=0.13.0
Requires-Dist: accelerate>=0.20.0
Requires-Dist: numpy>=1.21.0
Requires-Dist: peft>=0.6.0
Provides-Extra: dev
Requires-Dist: pytest>=7.0.0; extra == "dev"
Requires-Dist: black>=22.0.0; extra == "dev"
Requires-Dist: isort>=5.10.0; extra == "dev"
Requires-Dist: flake8>=5.0.0; extra == "dev"
Requires-Dist: mypy>=1.0.0; extra == "dev"
Provides-Extra: test
Requires-Dist: pytest>=7.0.0; extra == "test"
Requires-Dist: pytest-cov>=4.0.0; extra == "test"
Provides-Extra: docs
Requires-Dist: sphinx>=5.0.0; extra == "docs"
Requires-Dist: sphinx-rtd-theme>=1.0.0; extra == "docs"
Dynamic: license-file
